CHANGELOG.md
MANIFEST.in
README.md
setup.cfg
setup.py
Corporal.egg-info/PKG-INFO
Corporal.egg-info/SOURCES.txt
Corporal.egg-info/dependency_links.txt
Corporal.egg-info/entry_points.txt
Corporal.egg-info/requires.txt
Corporal.egg-info/top_level.txt
corporal/__init__.py
corporal/_version.py
corporal/commands.py
corporal/config.py
corporal/emails.py
corporal/batch/__init__.py
corporal/batch/vendorcatalog.py
corporal/data/config/corporal-rattail.conf
corporal/data/config/corporal-web.conf
corporal/db/__init__.py
corporal/db/model.py
corporal/fablib/__init__.py
corporal/fablib/corporal.py
corporal/fablib/python.py
corporal/projects/__init__.py
corporal/projects/corepos_poser.py
corporal/projects/corporal.py
corporal/web/__init__.py
corporal/web/app.py
corporal/web/menus.py
corporal/web/subscribers.py
corporal/web/static/__init__.py
corporal/web/templates/base_meta.mako
corporal/web/views/__init__.py
corporal/web/views/essentials.py
corporal/web/views/projects.py
corporal/web/views/supplemental.py
corporal/web/views/typical.py