Metadata-Version: 2.1
Name: Corporal
Version: 0.1.14
Summary: Companion Back-end for CORE-POS
Home-page: https://rattailproject.org
Author: Lance Edgar
Author-email: lance@edbob.org
Classifier: Development Status :: 3 - Alpha
Classifier: Environment :: Console
Classifier: Environment :: Web Environment
Classifier: Framework :: Pyramid
Classifier: Intended Audience :: Developers
Classifier: Natural Language :: English
Classifier: Operating System :: POSIX :: Linux
Classifier: Programming Language :: Python
Classifier: Programming Language :: Python :: 3
Classifier: Topic :: Office/Business
